Metadata-Version: 1.1
Name: vec2img
Version: 0.1.0
Summary: convert OpenCV samples file to images
Home-page: https://github.com/midnightSuyama/vec2img
Author: midnightSuyama
Author-email: midnightSuyama@gmail.com
License: MIT
Keywords: opencv vec
Platform: UNKNOWN
Classifier: Development Status :: 3 - Alpha
Classifier: Environment :: Console
Classifier: License :: OSI Approved :: MIT License
